baraja/__init__.py
baraja/card.py
baraja/deck.py
baraja/exceptions.py
baraja-0.3.0.dist-info/AUTHORS.md
baraja-0.3.0.dist-info/LICENSE
baraja-0.3.0.dist-info/METADATA
baraja-0.3.0.dist-info/WHEEL
baraja-0.3.0.dist-info/top_level.txt
baraja-0.3.0.dist-info/RECORD
