Metadata-Version: 2.1
Name: baraja
Version: 0.3.0
Summary: A project for simulating card drawing mechanics
Home-page: https://gitlab.com/elmiko/baraja
Author: michael mccune
Author-email: msm@opbstudios.com
License: MIT
Platform: UNKNOWN
Classifier: Development Status :: 4 - Beta
Classifier: Intended Audience :: Developers
Classifier: License :: OSI Approved :: MIT License
Classifier: Programming Language :: Python :: 3.9
Requires-Python: >=3.9
